verysimple/__init__.py
verysimple/add.py
verysimple/minus.py
verysimple/extras/__init__.py
verysimple/extras/multiply.py
verysimple1/__init__.py
verysimple1/add.py
verysimple1/minus.py
verysimple1/extras/__init__.py
verysimple1/extras/multiply.py
verysimple23/__init__.py
verysimple23/add.py
verysimple23/minus.py
verysimple23/extras/__init__.py
verysimple23/extras/multiply.py
verysimple24/__init__.py
verysimple24/add.py
verysimple24/minus.py
verysimple24/extras/__init__.py
verysimple24/extras/multiply.py
verysimple24-0.24.dist-info/METADATA
verysimple24-0.24.dist-info/WHEEL
verysimple24-0.24.dist-info/top_level.txt
verysimple24-0.24.dist-info/RECORD
